_pyquickjs.cpython-38-aarch64-linux-gnu.so
pyquickjs/__init__.py
pyquickjs-1.24.4.4.dist-info/LICENSE
pyquickjs-1.24.4.4.dist-info/METADATA
pyquickjs-1.24.4.4.dist-info/WHEEL
pyquickjs-1.24.4.4.dist-info/top_level.txt
pyquickjs-1.24.4.4.dist-info/RECORD
