Metadata-Version: 2.1
Name: pyquickjs
Version: 1.24.4.4
Summary: Wrapping the quickjs C library.
Home-page: https://github.com/hjdhnx/pyquickjs
Author: Petter Strandmark
Author-email: petter.strandmark@gmail.com
Maintainer: hjdhnx
Maintainer-email: 434857005@qq.com
License: UNKNOWN
Platform: UNKNOWN
